setup.cfg
setup.py
script/retina_viewer.py
simretina/__about__.py
simretina/__init__.py
simretina/dataset.py
simretina/gui.py
simretina/retina.py
simretina.egg-info/PKG-INFO
simretina.egg-info/SOURCES.txt
simretina.egg-info/dependency_links.txt
simretina.egg-info/pbr.json
simretina.egg-info/top_level.txt
simretina/retina-data/HorseRiding.avi
simretina/retina-data/TaiChi.avi
simretina/retina-data/dog.jpg
simretina/retina-data/lenna.png
simretina/retina-data/yuhuang-hu-photo.png