Metadata-Version: 1.1
Name: simretina
Version: 0.1.2
Summary: Simulation of the Retina with OpenCV.
Home-page: https://github.com/duguyue100/retina-simulation
Author: Yuhuang Hu, Sonali Andani
Author-email: yuhuang.hu@uzh.ch, andanis@student.ethz.ch
License: UNKNOWN
Download-URL: https://github.com/duguyue100/retina-simulation/tarball/0.1.2
Platform: UNKNOWN
Classifier: Development Status :: 4 - Beta
Classifier: Intended Audience :: Science/Research
Classifier: Natural Language :: English
Classifier: Operating System :: OS Independent
Classifier: Programming Language :: Python :: 2.7
Classifier: Programming Language :: Python :: 3.4
Classifier: Programming Language :: Python :: 3.5
Classifier: Topic :: Utilities
Classifier: Topic :: Scientific/Engineering
Classifier: Topic :: Scientific/Engineering :: Image Recognition
Classifier: Topic :: Scientific/Engineering :: Visualization
Classifier: Topic :: Software Development :: Libraries :: Python Modules
Classifier: License :: OSI Approved :: MIT License
